setup.cfg
setup.py
sqlzen/__init__.py
sqlzen.egg-info/PKG-INFO
sqlzen.egg-info/SOURCES.txt
sqlzen.egg-info/dependency_links.txt
sqlzen.egg-info/requires.txt
sqlzen.egg-info/top_level.txt