Metadata-Version: 1.1
Name: sqlzen
Version: 0.4.0
Summary: Because sometimes you want raw SQL
Home-page: https://github.com/creese/sqlzen
Author: Charles Reese
Author-email: charlespreese@gmail.com
License: UNKNOWN
Download-URL: https://github.com/creese/sqlzen/archive/0.4.0.zip
Platform: UNKNOWN
